data_delivery_spark_py/__init__.py
data_delivery_spark_py/test_utils/__init__.py
data_delivery_spark_py/test_utils/spark_session_manager.py
aissemble_extensions_data_delivery_spark_py-2.0.0.dist-info/LICENSE
aissemble_extensions_data_delivery_spark_py-2.0.0.dist-info/METADATA
aissemble_extensions_data_delivery_spark_py-2.0.0.dist-info/WHEEL
aissemble_extensions_data_delivery_spark_py-2.0.0.dist-info/RECORD
